setup.cfg
setup.py
anidex/Anidex.py
anidex/__init__.py
anidex/constants.py
anidex/helpers.py
anidex.egg-info/PKG-INFO
anidex.egg-info/SOURCES.txt
anidex.egg-info/dependency_links.txt
anidex.egg-info/requires.txt
anidex.egg-info/top_level.txt
examples/__init__.py
examples/basic_search.py
examples/connect.py
examples/search_with_query.py