Metadata-Version: 1.1
Name: anidex
Version: 0.2
Summary: A Python client library for anidex!
Home-page: https://github.com/stackexploit/pyanidex
Author: stackexploit
Author-email: stackexploit@protonmail.ch
License: UNKNOWN
Platform: UNKNOWN
Classifier: Operating System :: POSIX
Classifier: Operating System :: Microsoft :: Windows
Classifier: Operating System :: MacOS :: MacOS X
Classifier: Programming Language :: Python
Classifier: Programming Language :: Python :: 3.2
Classifier: Programming Language :: Python :: 3.3
Classifier: Programming Language :: Python :: 3.4
Classifier: Programming Language :: Python :: 3.5
Classifier: Programming Language :: Python :: 3.6
Classifier: Programming Language :: Python :: 3 :: Only
